{"chunk_definitions":[{"row":58,"row_count":1,"visible":true,"expansion_state":0,"options":{"engine":"r","label":"load-packages","include":false},"document_id":"F4CD58DE","chunk_id":"cgghjkxhwz19v","chunk_label":"load-packages"},{"row":65,"row_count":1,"visible":true,"expansion_state":0,"options":{"engine":"r","label":"connect-to-akfin","include":false},"document_id":"F4CD58DE","chunk_id":"cherucs2xqqu6","chunk_label":"connect-to-akfin"},{"row":100,"row_count":1,"visible":true,"expansion_state":0,"options":{"engine":"r","label":"query-cas","include":false},"document_id":"F4CD58DE","chunk_id":"c4ra4u4j2bk74","chunk_label":"query-cas"},{"row":144,"row_count":1,"visible":true,"expansion_state":0,"options":{"engine":"r","label":"process-cas","include":false},"document_id":"F4CD58DE","chunk_id":"cf5uv8v8r2w2j","chunk_label":"process-cas"},{"row":183,"row_count":1,"visible":true,"expansion_state":0,"options":{"engine":"r","label":"query-norpac-length","include":false},"document_id":"F4CD58DE","chunk_id":"c74cyqmbblfgj","chunk_label":"query-norpac-length"},{"row":224,"row_count":1,"visible":true,"expansion_state":0,"options":{"engine":"r","label":"query-norpac-age","include":false},"document_id":"F4CD58DE","chunk_id":"c8jfeq6g64oxh","chunk_label":"query-norpac-age"},{"row":270,"row_count":1,"visible":true,"expansion_state":0,"options":{"engine":"r","warning":false,"message":false,"echo":false,"label":"unnamed-chunk-65"},"document_id":"F4CD58DE","chunk_id":"cnny54llnhoxi","chunk_label":"unnamed-chunk-1"},{"row":296,"row_count":1,"visible":true,"expansion_state":0,"options":{"engine":"r","warning":false,"message":false,"echo":false,"label":"unnamed-chunk-66"},"document_id":"F4CD58DE","chunk_id":"c8cs0y2kz2kiu","chunk_label":"unnamed-chunk-2"},{"row":324,"row_count":1,"visible":true,"expansion_state":0,"options":{"engine":"r","warning":false,"message":false,"echo":false,"label":"unnamed-chunk-67"},"document_id":"F4CD58DE","chunk_id":"c80pbybldgekm","chunk_label":"unnamed-chunk-3"},{"row":377,"row_count":1,"visible":true,"expansion_state":0,"options":{},"document_id":"F4CD58DE","chunk_id":"cwywp84maw21z","chunk_label":"fig1"},{"row":414,"row_count":1,"visible":true,"expansion_state":0,"options":{},"document_id":"F4CD58DE","chunk_id":"csncltud73jj5","chunk_label":"fig2"},{"row":456,"row_count":1,"visible":true,"expansion_state":0,"options":{},"document_id":"F4CD58DE","chunk_id":"cdduce6zcfbgw","chunk_label":"fig3"},{"row":503,"row_count":1,"visible":true,"expansion_state":0,"options":{},"document_id":"F4CD58DE","chunk_id":"cedvjtmebjeu2","chunk_label":"fig4"},{"row":536,"row_count":1,"visible":true,"expansion_state":0,"options":{},"document_id":"F4CD58DE","chunk_id":"cs1gjolfl30zk","chunk_label":"fig5"},{"row":574,"row_count":1,"visible":true,"expansion_state":0,"options":{},"document_id":"F4CD58DE","chunk_id":"cgyx7pvb77imy","chunk_label":"fig6"},{"row":628,"row_count":1,"visible":true,"expansion_state":0,"options":{},"document_id":"F4CD58DE","chunk_id":"chs78tsj9gi3q","chunk_label":"fig7"},{"row":721,"row_count":1,"visible":true,"expansion_state":0,"options":{},"document_id":"F4CD58DE","chunk_id":"c4ozifikfacr6","chunk_label":"fig9"},{"row":759,"row_count":1,"visible":true,"expansion_state":0,"options":{},"document_id":"EE9BD729","chunk_id":"cbirtzm1711wo","chunk_label":"unnamed-chunk-4"},{"row":803,"row_count":1,"visible":true,"expansion_state":0,"options":{},"document_id":"F4CD58DE","chunk_id":"ciqn0tuj3bdsb","chunk_label":"fig10"},{"row":846,"row_count":1,"visible":true,"expansion_state":0,"options":{},"document_id":"EE9BD729","chunk_id":"ct7an52ommxpb","chunk_label":"fig11"}],"doc_write_time":1690234378}